###########################################################################################################
<cache>10800</cache>
<thumbnail>http://thetvdb.com/banners/seasons/5382-3.jpg</thumbnail>
<fanart>http://thetvdb.com/banners/fanart/original/77054-4.jpg</fanart>
#######################################################################################################################################
<item>
	<title>Garfield and Friends S03E01 - Skyway Robbery</title>
	<meta>
		<content>episode</content>
		<imdb>tt0094469</imdb>
		<tvdb>77054</tvdb>
		<tvshowtitle>Garfield and Friends</tvshowtitle>
		<year>1988</year>
		<title>Skyway Robbery</title>
		<premiered>1990-09-15</premiered>
		<season>3</season>
		<episode>1</episode>
		<thumbnail>http://thetvdb.com/banners/episodes/77054/226269.jpg</thumbnail>
		</meta>
	<link>
		<sublink>search</sublink>
		<sublink>searchsd</sublink>
	</link>
</item>

<item>
	<title>Garfield and Friends S03E02 - The Bunny Rabbits is Coming</title>
	<meta>
		<content>episode</content>
		<imdb>tt0094469</imdb>
		<tvdb>77054</tvdb>
		<tvshowtitle>Garfield and Friends</tvshowtitle>
		<year>1988</year>
		<title>The Bunny Rabbits is Coming</title>
		<premiered>1990-09-15</premiered>
		<season>3</season>
		<episode>2</episode>
		<thumbnail>http://thetvdb.com/banners/episodes/77054/226271.jpg</thumbnail>
		</meta>
	<link>
		<sublink>search</sublink>
		<sublink>searchsd</sublink>
	</link>
</item>

<item>
	<title>Garfield and Friends S03E03 - Close Encounters of the Garfield Kind</title>
	<meta>
		<content>episode</content>
		<imdb>tt0094469</imdb>
		<tvdb>77054</tvdb>
		<tvshowtitle>Garfield and Friends</tvshowtitle>
		<year>1988</year>
		<title>Close Encounters of the Garfield Kind</title>
		<premiered>1990-09-15</premiered>
		<season>3</season>
		<episode>3</episode>
		<thumbnail>http://thetvdb.com/banners/episodes/77054/226270.jpg</thumbnail>
		</meta>
	<link>
		<sublink>search</sublink>
		<sublink>searchsd</sublink>
	</link>
</item>

<item>
	<title>Garfield and Friends S03E04 - Astrocat</title>
	<meta>
		<content>episode</content>
		<imdb>tt0094469</imdb>
		<tvdb>77054</tvdb>
		<tvshowtitle>Garfield and Friends</tvshowtitle>
		<year>1988</year>
		<title>Astrocat</title>
		<premiered>1990-09-15</premiered>
		<season>3</season>
		<episode>4</episode>
		<thumbnail>http://thetvdb.com/banners/episodes/77054/226273.jpg</thumbnail>
		</meta>
	<link>
		<sublink>search</sublink>
		<sublink>searchsd</sublink>
	</link>
</item>

<item>
	<title>Garfield and Friends S03E05 - Cock-a-Doodle Duel</title>
	<meta>
		<content>episode</content>
		<imdb>tt0094469</imdb>
		<tvdb>77054</tvdb>
		<tvshowtitle>Garfield and Friends</tvshowtitle>
		<year>1988</year>
		<title>Cock-a-Doodle Duel</title>
		<premiered>1990-09-15</premiered>
		<season>3</season>
		<episode>5</episode>
		<thumbnail>http://thetvdb.com/banners/episodes/77054/226274.jpg</thumbnail>
		</meta>
	<link>
		<sublink>search</sublink>
		<sublink>searchsd</sublink>
	</link>
</item>

<item>
	<title>Garfield and Friends S03E06 - Cinderella Cat</title>
	<meta>
		<content>episode</content>
		<imdb>tt0094469</imdb>
		<tvdb>77054</tvdb>
		<tvshowtitle>Garfield and Friends</tvshowtitle>
		<year>1988</year>
		<title>Cinderella Cat</title>
		<premiered>1990-09-15</premiered>
		<season>3</season>
		<episode>6</episode>
		<thumbnail>http://thetvdb.com/banners/episodes/77054/226272.jpg</thumbnail>
		</meta>
	<link>
		<sublink>search</sublink>
		<sublink>searchsd</sublink>
	</link>
</item>

<item>
	<title>Garfield and Friends S03E07 - Ship Shape</title>
	<meta>
		<content>episode</content>
		<imdb>tt0094469</imdb>
		<tvdb>77054</tvdb>
		<tvshowtitle>Garfield and Friends</tvshowtitle>
		<year>1988</year>
		<title>Ship Shape</title>
		<premiered>1990-09-22</premiered>
		<season>3</season>
		<episode>7</episode>
		<thumbnail>http://thetvdb.com/banners/episodes/77054/226275.jpg</thumbnail>
		</meta>
	<link>
		<sublink>search</sublink>
		<sublink>searchsd</sublink>
	</link>
</item>

<item>
	<title>Garfield and Friends S03E08 - Barn of Fear II</title>
	<meta>
		<content>episode</content>
		<imdb>tt0094469</imdb>
		<tvdb>77054</tvdb>
		<tvshowtitle>Garfield and Friends</tvshowtitle>
		<year>1988</year>
		<title>Barn of Fear II</title>
		<premiered>1990-09-22</premiered>
		<season>3</season>
		<episode>8</episode>
		<thumbnail>http://thetvdb.com/banners/episodes/77054/226277.jpg</thumbnail>
		</meta>
	<link>
		<sublink>search</sublink>
		<sublink>searchsd</sublink>
	</link>
</item>

<item>
	<title>Garfield and Friends S03E09 - Break a Leg</title>
	<meta>
		<content>episode</content>
		<imdb>tt0094469</imdb>
		<tvdb>77054</tvdb>
		<tvshowtitle>Garfield and Friends</tvshowtitle>
		<year>1988</year>
		<title>Break a Leg</title>
		<premiered>1990-09-22</premiered>
		<season>3</season>
		<episode>9</episode>
		<thumbnail>http://thetvdb.com/banners/episodes/77054/226276.jpg</thumbnail>
		</meta>
	<link>
		<sublink>search</sublink>
		<sublink>searchsd</sublink>
	</link>
</item>

<item>
	<title>Garfield and Friends S03E10 - Twice Told Tale</title>
	<meta>
		<content>episode</content>
		<imdb>tt0094469</imdb>
		<tvdb>77054</tvdb>
		<tvshowtitle>Garfield and Friends</tvshowtitle>
		<year>1988</year>
		<title>Twice Told Tale</title>
		<premiered>1990-09-22</premiered>
		<season>3</season>
		<episode>10</episode>
		<thumbnail>http://thetvdb.com/banners/episodes/77054/226278.jpg</thumbnail>
		</meta>
	<link>
		<sublink>search</sublink>
		<sublink>searchsd</sublink>
	</link>
</item>

<item>
	<title>Garfield and Friends S03E11 - Orson Goes on Vacation</title>
	<meta>
		<content>episode</content>
		<imdb>tt0094469</imdb>
		<tvdb>77054</tvdb>
		<tvshowtitle>Garfield and Friends</tvshowtitle>
		<year>1988</year>
		<title>Orson Goes on Vacation</title>
		<premiered>1990-09-22</premiered>
		<season>3</season>
		<episode>11</episode>
		<thumbnail>http://thetvdb.com/banners/episodes/77054/226280.jpg</thumbnail>
		</meta>
	<link>
		<sublink>search</sublink>
		<sublink>searchsd</sublink>
	</link>
</item>

<item>
	<title>Garfield and Friends S03E12 - Wedding Bell Blues</title>
	<meta>
		<content>episode</content>
		<imdb>tt0094469</imdb>
		<tvdb>77054</tvdb>
		<tvshowtitle>Garfield and Friends</tvshowtitle>
		<year>1988</year>
		<title>Wedding Bell Blues</title>
		<premiered>1990-09-22</premiered>
		<season>3</season>
		<episode>12</episode>
		<thumbnail>http://thetvdb.com/banners/episodes/77054/226279.jpg</thumbnail>
		</meta>
	<link>
		<sublink>search</sublink>
		<sublink>searchsd</sublink>
	</link>
</item>

<item>
	<title>Garfield and Friends S03E13 - Clean Sweep</title>
	<meta>
		<content>episode</content>
		<imdb>tt0094469</imdb>
		<tvdb>77054</tvdb>
		<tvshowtitle>Garfield and Friends</tvshowtitle>
		<year>1988</year>
		<title>Clean Sweep</title>
		<premiered>1990-09-29</premiered>
		<season>3</season>
		<episode>13</episode>
		<thumbnail>http://thetvdb.com/banners/episodes/77054/226281.jpg</thumbnail>
		</meta>
	<link>
		<sublink>search</sublink>
		<sublink>searchsd</sublink>
	</link>
</item>

<item>
	<title>Garfield and Friends S03E14 - Secrets of the Animated Cartoon</title>
	<meta>
		<content>episode</content>
		<imdb>tt0094469</imdb>
		<tvdb>77054</tvdb>
		<tvshowtitle>Garfield and Friends</tvshowtitle>
		<year>1988</year>
		<title>Secrets of the Animated Cartoon</title>
		<premiered>1990-09-29</premiered>
		<season>3</season>
		<episode>14</episode>
		<thumbnail>http://thetvdb.com/banners/episodes/77054/226283.jpg</thumbnail>
		</meta>
	<link>
		<sublink>search</sublink>
		<sublink>searchsd</sublink>
	</link>
</item>

<item>
	<title>Garfield and Friends S03E15 - How the West Was Lost</title>
	<meta>
		<content>episode</content>
		<imdb>tt0094469</imdb>
		<tvdb>77054</tvdb>
		<tvshowtitle>Garfield and Friends</tvshowtitle>
		<year>1988</year>
		<title>How the West Was Lost</title>
		<premiered>1990-09-29</premiered>
		<season>3</season>
		<episode>15</episode>
		<thumbnail>http://thetvdb.com/banners/episodes/77054/226282.jpg</thumbnail>
		</meta>
	<link>
		<sublink>search</sublink>
		<sublink>searchsd</sublink>
	</link>
</item>

<item>
	<title>Garfield and Friends S03E16 - Binky Gets Cancelled...Again!</title>
	<meta>
		<content>episode</content>
		<imdb>tt0094469</imdb>
		<tvdb>77054</tvdb>
		<tvshowtitle>Garfield and Friends</tvshowtitle>
		<year>1988</year>
		<title>Binky Gets Cancelled...Again!</title>
		<premiered>1990-09-29</premiered>
		<season>3</season>
		<episode>16</episode>
		<thumbnail>http://thetvdb.com/banners/episodes/77054/226284.jpg</thumbnail>
		</meta>
	<link>
		<sublink>search</sublink>
		<sublink>searchsd</sublink>
	</link>
</item>

<item>
	<title>Garfield and Friends S03E17 - Orson's Diner</title>
	<meta>
		<content>episode</content>
		<imdb>tt0094469</imdb>
		<tvdb>77054</tvdb>
		<tvshowtitle>Garfield and Friends</tvshowtitle>
		<year>1988</year>
		<title>Orson's Diner</title>
		<premiered>1990-09-29</premiered>
		<season>3</season>
		<episode>17</episode>
		<thumbnail>http://thetvdb.com/banners/episodes/77054/226286.jpg</thumbnail>
		</meta>
	<link>
		<sublink>search</sublink>
		<sublink>searchsd</sublink>
	</link>
</item>

<item>
	<title>Garfield and Friends S03E18 - Flat Tired</title>
	<meta>
		<content>episode</content>
		<imdb>tt0094469</imdb>
		<tvdb>77054</tvdb>
		<tvshowtitle>Garfield and Friends</tvshowtitle>
		<year>1988</year>
		<title>Flat Tired</title>
		<premiered>1990-09-29</premiered>
		<season>3</season>
		<episode>18</episode>
		<thumbnail>http://thetvdb.com/banners/episodes/77054/226285.jpg</thumbnail>
		</meta>
	<link>
		<sublink>search</sublink>
		<sublink>searchsd</sublink>
	</link>
</item>

<item>
	<title>Garfield and Friends S03E19 - Return of the Buddy Bears</title>
	<meta>
		<content>episode</content>
		<imdb>tt0094469</imdb>
		<tvdb>77054</tvdb>
		<tvshowtitle>Garfield and Friends</tvshowtitle>
		<year>1988</year>
		<title>Return of the Buddy Bears</title>
		<premiered>1990-10-06</premiered>
		<season>3</season>
		<episode>19</episode>
		<thumbnail>http://thetvdb.com/banners/episodes/77054/226287.jpg</thumbnail>
		</meta>
	<link>
		<sublink>search</sublink>
		<sublink>searchsd</sublink>
	</link>
</item>

<item>
	<title>Garfield and Friends S03E20 - Much Ado About Lanolin</title>
	<meta>
		<content>episode</content>
		<imdb>tt0094469</imdb>
		<tvdb>77054</tvdb>
		<tvshowtitle>Garfield and Friends</tvshowtitle>
		<year>1988</year>
		<title>Much Ado About Lanolin</title>
		<premiered>1990-10-06</premiered>
		<season>3</season>
		<episode>20</episode>
		<thumbnail>http://thetvdb.com/banners/episodes/77054/226289.jpg</thumbnail>
		</meta>
	<link>
		<sublink>search</sublink>
		<sublink>searchsd</sublink>
	</link>
</item>

<item>
	<title>Garfield and Friends S03E21 - Reigning Cats and Dogs</title>
	<meta>
		<content>episode</content>
		<imdb>tt0094469</imdb>
		<tvdb>77054</tvdb>
		<tvshowtitle>Garfield and Friends</tvshowtitle>
		<year>1988</year>
		<title>Reigning Cats and Dogs</title>
		<premiered>1990-10-06</premiered>
		<season>3</season>
		<episode>21</episode>
		<thumbnail>http://thetvdb.com/banners/episodes/77054/226288.jpg</thumbnail>
		</meta>
	<link>
		<sublink>search</sublink>
		<sublink>searchsd</sublink>
	</link>
</item>

<item>
	<title>Garfield and Friends S03E22 - Fit for a King</title>
	<meta>
		<content>episode</content>
		<imdb>tt0094469</imdb>
		<tvdb>77054</tvdb>
		<tvshowtitle>Garfield and Friends</tvshowtitle>
		<year>1988</year>
		<title>Fit for a King</title>
		<premiered>1990-10-06</premiered>
		<season>3</season>
		<episode>22</episode>
		<thumbnail>http://thetvdb.com/banners/episodes/77054/226290.jpg</thumbnail>
		</meta>
	<link>
		<sublink>search</sublink>
		<sublink>searchsd</sublink>
	</link>
</item>

<item>
	<title>Garfield and Friends S03E23 - Ben Hog</title>
	<meta>
		<content>episode</content>
		<imdb>tt0094469</imdb>
		<tvdb>77054</tvdb>
		<tvshowtitle>Garfield and Friends</tvshowtitle>
		<year>1988</year>
		<title>Ben Hog</title>
		<premiered>1990-10-06</premiered>
		<season>3</season>
		<episode>23</episode>
		<thumbnail>http://thetvdb.com/banners/episodes/77054/226292.jpg</thumbnail>
		</meta>
	<link>
		<sublink>search</sublink>
		<sublink>searchsd</sublink>
	</link>
</item>

<item>
	<title>Garfield and Friends S03E24 - Dessert in the Desert</title>
	<meta>
		<content>episode</content>
		<imdb>tt0094469</imdb>
		<tvdb>77054</tvdb>
		<tvshowtitle>Garfield and Friends</tvshowtitle>
		<year>1988</year>
		<title>Dessert in the Desert</title>
		<premiered>1990-10-06</premiered>
		<season>3</season>
		<episode>24</episode>
		<thumbnail>http://thetvdb.com/banners/episodes/77054/226291.jpg</thumbnail>
		</meta>
	<link>
		<sublink>search</sublink>
		<sublink>searchsd</sublink>
	</link>
</item>

<item>
	<title>Garfield and Friends S03E25 - The Hound of the Arbuckles</title>
	<meta>
		<content>episode</content>
		<imdb>tt0094469</imdb>
		<tvdb>77054</tvdb>
		<tvshowtitle>Garfield and Friends</tvshowtitle>
		<year>1988</year>
		<title>The Hound of the Arbuckles</title>
		<premiered>1990-10-13</premiered>
		<season>3</season>
		<episode>25</episode>
		<thumbnail>http://thetvdb.com/banners/episodes/77054/226293.jpg</thumbnail>
		</meta>
	<link>
		<sublink>search</sublink>
		<sublink>searchsd</sublink>
	</link>
</item>

<item>
	<title>Garfield and Friends S03E26 - Read Alert</title>
	<meta>
		<content>episode</content>
		<imdb>tt0094469</imdb>
		<tvdb>77054</tvdb>
		<tvshowtitle>Garfield and Friends</tvshowtitle>
		<year>1988</year>
		<title>Read Alert</title>
		<premiered>1990-10-13</premiered>
		<season>3</season>
		<episode>26</episode>
		<thumbnail>http://thetvdb.com/banners/episodes/77054/226295.jpg</thumbnail>
		</meta>
	<link>
		<sublink>search</sublink>
		<sublink>searchsd</sublink>
	</link>
</item>

<item>
	<title>Garfield and Friends S03E27 - Urban Arbuckle</title>
	<meta>
		<content>episode</content>
		<imdb>tt0094469</imdb>
		<tvdb>77054</tvdb>
		<tvshowtitle>Garfield and Friends</tvshowtitle>
		<year>1988</year>
		<title>Urban Arbuckle</title>
		<premiered>1990-10-13</premiered>
		<season>3</season>
		<episode>27</episode>
		<thumbnail>http://thetvdb.com/banners/episodes/77054/226294.jpg</thumbnail>
		</meta>
	<link>
		<sublink>search</sublink>
		<sublink>searchsd</sublink>
	</link>
</item>

<item>
	<title>Garfield and Friends S03E28 - Odielocks and the Three Cats</title>
	<meta>
		<content>episode</content>
		<imdb>tt0094469</imdb>
		<tvdb>77054</tvdb>
		<tvshowtitle>Garfield and Friends</tvshowtitle>
		<year>1988</year>
		<title>Odielocks and the Three Cats</title>
		<premiered>1990-10-13</premiered>
		<season>3</season>
		<episode>28</episode>
		<thumbnail>http://thetvdb.com/banners/episodes/77054/226296.jpg</thumbnail>
		</meta>
	<link>
		<sublink>search</sublink>
		<sublink>searchsd</sublink>
	</link>
</item>

<item>
	<title>Garfield and Friends S03E29 - Quack to the Future</title>
	<meta>
		<content>episode</content>
		<imdb>tt0094469</imdb>
		<tvdb>77054</tvdb>
		<tvshowtitle>Garfield and Friends</tvshowtitle>
		<year>1988</year>
		<title>Quack to the Future</title>
		<premiered>1990-10-13</premiered>
		<season>3</season>
		<episode>29</episode>
		<thumbnail>http://thetvdb.com/banners/episodes/77054/226298.jpg</thumbnail>
		</meta>
	<link>
		<sublink>search</sublink>
		<sublink>searchsd</sublink>
	</link>
</item>

<item>
	<title>Garfield and Friends S03E30 - Beddy Buy</title>
	<meta>
		<content>episode</content>
		<imdb>tt0094469</imdb>
		<tvdb>77054</tvdb>
		<tvshowtitle>Garfield and Friends</tvshowtitle>
		<year>1988</year>
		<title>Beddy Buy</title>
		<premiered>1990-10-13</premiered>
		<season>3</season>
		<episode>30</episode>
		<thumbnail>http://thetvdb.com/banners/episodes/77054/226297.jpg</thumbnail>
		</meta>
	<link>
		<sublink>search</sublink>
		<sublink>searchsd</sublink>
	</link>
</item>

<item>
	<title>Garfield and Friends S03E31 - Count Lasagna</title>
	<meta>
		<content>episode</content>
		<imdb>tt0094469</imdb>
		<tvdb>77054</tvdb>
		<tvshowtitle>Garfield and Friends</tvshowtitle>
		<year>1988</year>
		<title>Count Lasagna</title>
		<premiered>1990-10-20</premiered>
		<season>3</season>
		<episode>31</episode>
		<thumbnail>http://thetvdb.com/banners/episodes/77054/226299.jpg</thumbnail>
		</meta>
	<link>
		<sublink>search</sublink>
		<sublink>searchsd</sublink>
	</link>
</item>

<item>
	<title>Garfield and Friends S03E32 - Mystery Guest</title>
	<meta>
		<content>episode</content>
		<imdb>tt0094469</imdb>
		<tvdb>77054</tvdb>
		<tvshowtitle>Garfield and Friends</tvshowtitle>
		<year>1988</year>
		<title>Mystery Guest</title>
		<premiered>1990-10-20</premiered>
		<season>3</season>
		<episode>32</episode>
		<thumbnail>http://thetvdb.com/banners/episodes/77054/226301.jpg</thumbnail>
		</meta>
	<link>
		<sublink>search</sublink>
		<sublink>searchsd</sublink>
	</link>
</item>

<item>
	<title>Garfield and Friends S03E33 - Rodent Rampage</title>
	<meta>
		<content>episode</content>
		<imdb>tt0094469</imdb>
		<tvdb>77054</tvdb>
		<tvshowtitle>Garfield and Friends</tvshowtitle>
		<year>1988</year>
		<title>Rodent Rampage</title>
		<premiered>1990-10-20</premiered>
		<season>3</season>
		<episode>33</episode>
		<thumbnail>http://thetvdb.com/banners/episodes/77054/226300.jpg</thumbnail>
		</meta>
	<link>
		<sublink>search</sublink>
		<sublink>searchsd</sublink>
	</link>
</item>

<item>
	<title>Garfield and Friends S03E34 - Feline Felon</title>
	<meta>
		<content>episode</content>
		<imdb>tt0094469</imdb>
		<tvdb>77054</tvdb>
		<tvshowtitle>Garfield and Friends</tvshowtitle>
		<year>1988</year>
		<title>Feline Felon</title>
		<premiered>1990-10-20</premiered>
		<season>3</season>
		<episode>34</episode>
		<thumbnail>http://thetvdb.com/banners/episodes/77054/226302.jpg</thumbnail>
		</meta>
	<link>
		<sublink>search</sublink>
		<sublink>searchsd</sublink>
	</link>
</item>

<item>
	<title>Garfield and Friends S03E35 - The Legal Eagle</title>
	<meta>
		<content>episode</content>
		<imdb>tt0094469</imdb>
		<tvdb>77054</tvdb>
		<tvshowtitle>Garfield and Friends</tvshowtitle>
		<year>1988</year>
		<title>The Legal Eagle</title>
		<premiered>1990-10-20</premiered>
		<season>3</season>
		<episode>35</episode>
		<thumbnail>http://thetvdb.com/banners/episodes/77054/226304.jpg</thumbnail>
		</meta>
	<link>
		<sublink>search</sublink>
		<sublink>searchsd</sublink>
	</link>
</item>

<item>
	<title>Garfield and Friends S03E36 - The Cactus Saga</title>
	<meta>
		<content>episode</content>
		<imdb>tt0094469</imdb>
		<tvdb>77054</tvdb>
		<tvshowtitle>Garfield and Friends</tvshowtitle>
		<year>1988</year>
		<title>The Cactus Saga</title>
		<premiered>1990-10-20</premiered>
		<season>3</season>
		<episode>36</episode>
		<thumbnail>http://thetvdb.com/banners/episodes/77054/226303.jpg</thumbnail>
		</meta>
	<link>
		<sublink>search</sublink>
		<sublink>searchsd</sublink>
	</link>
</item>

<item>
	<title>Garfield and Friends S03E37 - D.J. Jon</title>
	<meta>
		<content>episode</content>
		<imdb>tt0094469</imdb>
		<tvdb>77054</tvdb>
		<tvshowtitle>Garfield and Friends</tvshowtitle>
		<year>1988</year>
		<title>D.J. Jon</title>
		<premiered>1990-10-27</premiered>
		<season>3</season>
		<episode>37</episode>
		<thumbnail>http://thetvdb.com/banners/episodes/77054/226305.jpg</thumbnail>
		</meta>
	<link>
		<sublink>search</sublink>
		<sublink>searchsd</sublink>
	</link>
</item>

<item>
	<title>Garfield and Friends S03E38 - Cornfinger</title>
	<meta>
		<content>episode</content>
		<imdb>tt0094469</imdb>
		<tvdb>77054</tvdb>
		<tvshowtitle>Garfield and Friends</tvshowtitle>
		<year>1988</year>
		<title>Cornfinger</title>
		<premiered>1990-10-27</premiered>
		<season>3</season>
		<episode>38</episode>
		<thumbnail>http://thetvdb.com/banners/episodes/77054/226307.jpg</thumbnail>
		</meta>
	<link>
		<sublink>search</sublink>
		<sublink>searchsd</sublink>
	</link>
</item>

<item>
	<title>Garfield and Friends S03E39 - Five Minute Warning</title>
	<meta>
		<content>episode</content>
		<imdb>tt0094469</imdb>
		<tvdb>77054</tvdb>
		<tvshowtitle>Garfield and Friends</tvshowtitle>
		<year>1988</year>
		<title>Five Minute Warning</title>
		<premiered>1990-10-27</premiered>
		<season>3</season>
		<episode>39</episode>
		<thumbnail>http://thetvdb.com/banners/episodes/77054/226306.jpg</thumbnail>
		</meta>
	<link>
		<sublink>search</sublink>
		<sublink>searchsd</sublink>
	</link>
</item>

<item>
	<title>Garfield and Friends S03E40 - Wonderful World</title>
	<meta>
		<content>episode</content>
		<imdb>tt0094469</imdb>
		<tvdb>77054</tvdb>
		<tvshowtitle>Garfield and Friends</tvshowtitle>
		<year>1988</year>
		<title>Wonderful World</title>
		<premiered>1990-10-27</premiered>
		<season>3</season>
		<episode>40</episode>
		<thumbnail>http://thetvdb.com/banners/episodes/77054/226308.jpg</thumbnail>
		</meta>
	<link>
		<sublink>search</sublink>
		<sublink>searchsd</sublink>
	</link>
</item>

<item>
	<title>Garfield and Friends S03E41 - The Orson Awards</title>
	<meta>
		<content>episode</content>
		<imdb>tt0094469</imdb>
		<tvdb>77054</tvdb>
		<tvshowtitle>Garfield and Friends</tvshowtitle>
		<year>1988</year>
		<title>The Orson Awards</title>
		<premiered>1990-10-27</premiered>
		<season>3</season>
		<episode>41</episode>
		<thumbnail>http://thetvdb.com/banners/episodes/77054/226310.jpg</thumbnail>
		</meta>
	<link>
		<sublink>search</sublink>
		<sublink>searchsd</sublink>
	</link>
</item>

<item>
	<title>Garfield and Friends S03E42 - The Garfield Workout</title>
	<meta>
		<content>episode</content>
		<imdb>tt0094469</imdb>
		<tvdb>77054</tvdb>
		<tvshowtitle>Garfield and Friends</tvshowtitle>
		<year>1988</year>
		<title>The Garfield Workout</title>
		<premiered>1990-10-27</premiered>
		<season>3</season>
		<episode>42</episode>
		<thumbnail>http://thetvdb.com/banners/episodes/77054/226309.jpg</thumbnail>
		</meta>
	<link>
		<sublink>search</sublink>
		<sublink>searchsd</sublink>
	</link>
</item>

<item>
	<title>Garfield and Friends S03E43 - All Things Fat and Small</title>
	<meta>
		<content>episode</content>
		<imdb>tt0094469</imdb>
		<tvdb>77054</tvdb>
		<tvshowtitle>Garfield and Friends</tvshowtitle>
		<year>1988</year>
		<title>All Things Fat and Small</title>
		<premiered>1990-11-03</premiered>
		<season>3</season>
		<episode>43</episode>
		<thumbnail>http://thetvdb.com/banners/episodes/77054/226311.jpg</thumbnail>
		</meta>
	<link>
		<sublink>search</sublink>
		<sublink>searchsd</sublink>
	</link>
</item>

<item>
	<title>Garfield and Friends S03E44 - Robin Hog</title>
	<meta>
		<content>episode</content>
		<imdb>tt0094469</imdb>
		<tvdb>77054</tvdb>
		<tvshowtitle>Garfield and Friends</tvshowtitle>
		<year>1988</year>
		<title>Robin Hog</title>
		<premiered>1990-11-03</premiered>
		<season>3</season>
		<episode>44</episode>
		<thumbnail>http://thetvdb.com/banners/episodes/77054/226313.jpg</thumbnail>
		</meta>
	<link>
		<sublink>search</sublink>
		<sublink>searchsd</sublink>
	</link>
</item>

<item>
	<title>Garfield and Friends S03E45 - Hare Replacement</title>
	<meta>
		<content>episode</content>
		<imdb>tt0094469</imdb>
		<tvdb>77054</tvdb>
		<tvshowtitle>Garfield and Friends</tvshowtitle>
		<year>1988</year>
		<title>Hare Replacement</title>
		<premiered>1990-11-03</premiered>
		<season>3</season>
		<episode>45</episode>
		<thumbnail>http://thetvdb.com/banners/episodes/77054/226312.jpg</thumbnail>
		</meta>
	<link>
		<sublink>search</sublink>
		<sublink>searchsd</sublink>
	</link>
</item>

<item>
	<title>Garfield and Friends S03E46 - Stick to It</title>
	<meta>
		<content>episode</content>
		<imdb>tt0094469</imdb>
		<tvdb>77054</tvdb>
		<tvshowtitle>Garfield and Friends</tvshowtitle>
		<year>1988</year>
		<title>Stick to It</title>
		<premiered>1990-11-10</premiered>
		<season>3</season>
		<episode>46</episode>
		<thumbnail>http://thetvdb.com/banners/episodes/77054/226314.jpg</thumbnail>
		</meta>
	<link>
		<sublink>search</sublink>
		<sublink>searchsd</sublink>
	</link>
</item>

<item>
	<title>Garfield and Friends S03E47 - Orson in Wonderland</title>
	<meta>
		<content>episode</content>
		<imdb>tt0094469</imdb>
		<tvdb>77054</tvdb>
		<tvshowtitle>Garfield and Friends</tvshowtitle>
		<year>1988</year>
		<title>Orson in Wonderland</title>
		<premiered>1990-11-10</premiered>
		<season>3</season>
		<episode>47</episode>
		<thumbnail>http://thetvdb.com/banners/episodes/77054/226316.jpg</thumbnail>
		</meta>
	<link>
		<sublink>search</sublink>
		<sublink>searchsd</sublink>
	</link>
</item>

<item>
	<title>Garfield and Friends S03E48 - For Cats Only</title>
	<meta>
		<content>episode</content>
		<imdb>tt0094469</imdb>
		<tvdb>77054</tvdb>
		<tvshowtitle>Garfield and Friends</tvshowtitle>
		<year>1988</year>
		<title>For Cats Only</title>
		<premiered>1990-11-10</premiered>
		<season>3</season>
		<episode>48</episode>
		<thumbnail>http://thetvdb.com/banners/episodes/77054/226315.jpg</thumbnail>
		</meta>
	<link>
		<sublink>search</sublink>
		<sublink>searchsd</sublink>
	</link>
</item>

<item>
	<title>Garfield and Friends S03E49 - Mistakes will Happen</title>
	<meta>
		<content>episode</content>
		<imdb>tt0094469</imdb>
		<tvdb>77054</tvdb>
		<tvshowtitle>Garfield and Friends</tvshowtitle>
		<year>1988</year>
		<title>Mistakes will Happen</title>
		<premiered>1990-11-17</premiered>
		<season>3</season>
		<episode>49</episode>
		<thumbnail>http://thetvdb.com/banners/episodes/77054/4143513.jpg</thumbnail>
		</meta>
	<link>
		<sublink>search</sublink>
		<sublink>searchsd</sublink>
	</link>
</item>

<item>
	<title>Garfield and Friends S03E50 - The Well Dweller</title>
	<meta>
		<content>episode</content>
		<imdb>tt0094469</imdb>
		<tvdb>77054</tvdb>
		<tvshowtitle>Garfield and Friends</tvshowtitle>
		<year>1988</year>
		<title>The Well Dweller</title>
		<premiered>1990-11-17</premiered>
		<season>3</season>
		<episode>50</episode>
		<thumbnail>http://thetvdb.com/banners/episodes/77054/4143514.jpg</thumbnail>
		</meta>
	<link>
		<sublink>search</sublink>
		<sublink>searchsd</sublink>
	</link>
</item>

<item>
	<title>Garfield and Friends S03E51 - The Wise Man</title>
	<meta>
		<content>episode</content>
		<imdb>tt0094469</imdb>
		<tvdb>77054</tvdb>
		<tvshowtitle>Garfield and Friends</tvshowtitle>
		<year>1988</year>
		<title>The Wise Man</title>
		<premiered>1990-11-17</premiered>
		<season>3</season>
		<episode>51</episode>
		<thumbnail>http://thetvdb.com/banners/episodes/77054/4143515.jpg</thumbnail>
		</meta>
	<link>
		<sublink>search</sublink>
		<sublink>searchsd</sublink>
	</link>
</item>

<item>
	<title>Garfield and Friends S03E52 - Star Struck</title>
	<meta>
		<content>episode</content>
		<imdb>tt0094469</imdb>
		<tvdb>77054</tvdb>
		<tvshowtitle>Garfield and Friends</tvshowtitle>
		<year>1988</year>
		<title>Star Struck</title>
		<premiered>1990-11-24</premiered>
		<season>3</season>
		<episode>52</episode>
		<thumbnail>http://thetvdb.com/banners/episodes/77054/226317.jpg</thumbnail>
		</meta>
	<link>
		<sublink>search</sublink>
		<sublink>searchsd</sublink>
	</link>
</item>

<item>
	<title>Garfield and Friends S03E53 - Election Daze</title>
	<meta>
		<content>episode</content>
		<imdb>tt0094469</imdb>
		<tvdb>77054</tvdb>
		<tvshowtitle>Garfield and Friends</tvshowtitle>
		<year>1988</year>
		<title>Election Daze</title>
		<premiered>1990-11-24</premiered>
		<season>3</season>
		<episode>53</episode>
		<thumbnail>http://thetvdb.com/banners/episodes/77054/226319.jpg</thumbnail>
		</meta>
	<link>
		<sublink>search</sublink>
		<sublink>searchsd</sublink>
	</link>
</item>

<item>
	<title>Garfield and Friends S03E54 - Dirty Business</title>
	<meta>
		<content>episode</content>
		<imdb>tt0094469</imdb>
		<tvdb>77054</tvdb>
		<tvshowtitle>Garfield and Friends</tvshowtitle>
		<year>1988</year>
		<title>Dirty Business</title>
		<premiered>1990-11-24</premiered>
		<season>3</season>
		<episode>54</episode>
		<thumbnail>http://thetvdb.com/banners/episodes/77054/226318.jpg</thumbnail>
		</meta>
	<link>
		<sublink>search</sublink>
		<sublink>searchsd</sublink>
	</link>
</item>
