###########################################################################################################
<cache>10800</cache>
<thumbnail>http://thetvdb.com/banners/seasons/79429-3-2.jpg</thumbnail>
<fanart>http://thetvdb.com/banners/fanart/original/79429-3.jpg</fanart>
#######################################################################################################################################
<item>
	<title>Curious George S03E01 - Ice Station Monkey</title>
	<meta>
		<content>episode</content>
		<imdb>tt0449545</imdb>
		<tvdb>79429</tvdb>
		<tvshowtitle>Curious George</tvshowtitle>
		<year>2006</year>
		<title>Ice Station Monkey</title>
		<premiered>2008-09-01</premiered>
		<season>3</season>
		<episode>1</episode>
		<thumbnail>http://thetvdb.com/banners/episodes/79429/403010.jpg</thumbnail>
		</meta>
	<link>
		<sublink>search</sublink>
		<sublink>searchsd</sublink>
	</link>
</item>

<item>
	<title>Curious George S03E02 - The Perfect Carrot</title>
	<meta>
		<content>episode</content>
		<imdb>tt0449545</imdb>
		<tvdb>79429</tvdb>
		<tvshowtitle>Curious George</tvshowtitle>
		<year>2006</year>
		<title>The Perfect Carrot</title>
		<premiered>2008-09-01</premiered>
		<season>3</season>
		<episode>2</episode>
		<thumbnail>http://thetvdb.com/banners/episodes/79429/403012.jpg</thumbnail>
		</meta>
	<link>
		<sublink>search</sublink>
		<sublink>searchsd</sublink>
	</link>
</item>

<item>
	<title>Curious George S03E03 - Curious George Meets The Press</title>
	<meta>
		<content>episode</content>
		<imdb>tt0449545</imdb>
		<tvdb>79429</tvdb>
		<tvshowtitle>Curious George</tvshowtitle>
		<year>2006</year>
		<title>Curious George Meets The Press</title>
		<premiered>2008-09-02</premiered>
		<season>3</season>
		<episode>3</episode>
		<thumbnail>http://thetvdb.com/banners/episodes/79429/403011.jpg</thumbnail>
		</meta>
	<link>
		<sublink>search</sublink>
		<sublink>searchsd</sublink>
	</link>
</item>

<item>
	<title>Curious George S03E04 - Snow Use</title>
	<meta>
		<content>episode</content>
		<imdb>tt0449545</imdb>
		<tvdb>79429</tvdb>
		<tvshowtitle>Curious George</tvshowtitle>
		<year>2006</year>
		<title>Snow Use</title>
		<premiered>2008-09-02</premiered>
		<season>3</season>
		<episode>4</episode>
		<thumbnail>http://thetvdb.com/banners/episodes/79429/403013.jpg</thumbnail>
		</meta>
	<link>
		<sublink>search</sublink>
		<sublink>searchsd</sublink>
	</link>
</item>

<item>
	<title>Curious George S03E05 - For the Birds</title>
	<meta>
		<content>episode</content>
		<imdb>tt0449545</imdb>
		<tvdb>79429</tvdb>
		<tvshowtitle>Curious George</tvshowtitle>
		<year>2006</year>
		<title>For the Birds</title>
		<premiered>2008-09-03</premiered>
		<season>3</season>
		<episode>5</episode>
		<thumbnail>http://thetvdb.com/banners/episodes/79429/1160811.jpg</thumbnail>
		</meta>
	<link>
		<sublink>search</sublink>
		<sublink>searchsd</sublink>
	</link>
</item>

<item>
	<title>Curious George S03E06 - Curious George-asaurus</title>
	<meta>
		<content>episode</content>
		<imdb>tt0449545</imdb>
		<tvdb>79429</tvdb>
		<tvshowtitle>Curious George</tvshowtitle>
		<year>2006</year>
		<title>Curious George-asaurus</title>
		<premiered>2008-09-03</premiered>
		<season>3</season>
		<episode>6</episode>
		<thumbnail>http://thetvdb.com/banners/episodes/79429/403015.jpg</thumbnail>
		</meta>
	<link>
		<sublink>search</sublink>
		<sublink>searchsd</sublink>
	</link>
</item>

<item>
	<title>Curious George S03E07 - Mulch Ado About Nothing</title>
	<meta>
		<content>episode</content>
		<imdb>tt0449545</imdb>
		<tvdb>79429</tvdb>
		<tvshowtitle>Curious George</tvshowtitle>
		<year>2006</year>
		<title>Mulch Ado About Nothing</title>
		<premiered>2008-09-04</premiered>
		<season>3</season>
		<episode>7</episode>
		<thumbnail>http://thetvdb.com/banners/episodes/79429/1228501.jpg</thumbnail>
		</meta>
	<link>
		<sublink>search</sublink>
		<sublink>searchsd</sublink>
	</link>
</item>

<item>
	<title>Curious George S03E08 - What Goes Up</title>
	<meta>
		<content>episode</content>
		<imdb>tt0449545</imdb>
		<tvdb>79429</tvdb>
		<tvshowtitle>Curious George</tvshowtitle>
		<year>2006</year>
		<title>What Goes Up</title>
		<premiered>2008-09-04</premiered>
		<season>3</season>
		<episode>8</episode>
		<thumbnail>http://thetvdb.com/banners/episodes/79429/1160801.jpg</thumbnail>
		</meta>
	<link>
		<sublink>search</sublink>
		<sublink>searchsd</sublink>
	</link>
</item>

<item>
	<title>Curious George S03E09 - Amazing Maze Race</title>
	<meta>
		<content>episode</content>
		<imdb>tt0449545</imdb>
		<tvdb>79429</tvdb>
		<tvshowtitle>Curious George</tvshowtitle>
		<year>2006</year>
		<title>Amazing Maze Race</title>
		<premiered>2008-10-13</premiered>
		<season>3</season>
		<episode>9</episode>
		<thumbnail>http://thetvdb.com/banners/episodes/79429/403014.jpg</thumbnail>
		</meta>
	<link>
		<sublink>search</sublink>
		<sublink>searchsd</sublink>
	</link>
</item>

<item>
	<title>Curious George S03E10 - The Color of Monkey</title>
	<meta>
		<content>episode</content>
		<imdb>tt0449545</imdb>
		<tvdb>79429</tvdb>
		<tvshowtitle>Curious George</tvshowtitle>
		<year>2006</year>
		<title>The Color of Monkey</title>
		<premiered>2008-10-13</premiered>
		<season>3</season>
		<episode>10</episode>
		<thumbnail>http://thetvdb.com/banners/episodes/79429/821091.jpg</thumbnail>
		</meta>
	<link>
		<sublink>search</sublink>
		<sublink>searchsd</sublink>
	</link>
</item>

<item>
	<title>Curious George S03E11 - Man with the Monkey Hands</title>
	<meta>
		<content>episode</content>
		<imdb>tt0449545</imdb>
		<tvdb>79429</tvdb>
		<tvshowtitle>Curious George</tvshowtitle>
		<year>2006</year>
		<title>Man with the Monkey Hands</title>
		<premiered>2008-11-28</premiered>
		<season>3</season>
		<episode>11</episode>
		<thumbnail>http://thetvdb.com/banners/episodes/79429/1228441.jpg</thumbnail>
		</meta>
	<link>
		<sublink>search</sublink>
		<sublink>searchsd</sublink>
	</link>
</item>

<item>
	<title>Curious George S03E12 - Whistlepig Wednesday</title>
	<meta>
		<content>episode</content>
		<imdb>tt0449545</imdb>
		<tvdb>79429</tvdb>
		<tvshowtitle>Curious George</tvshowtitle>
		<year>2006</year>
		<title>Whistlepig Wednesday</title>
		<premiered>2008-11-28</premiered>
		<season>3</season>
		<episode>12</episode>
		<thumbnail>http://thetvdb.com/banners/episodes/79429/639581.jpg</thumbnail>
		</meta>
	<link>
		<sublink>search</sublink>
		<sublink>searchsd</sublink>
	</link>
</item>

<item>
	<title>Curious George S03E13 - George Digs Worms</title>
	<meta>
		<content>episode</content>
		<imdb>tt0449545</imdb>
		<tvdb>79429</tvdb>
		<tvshowtitle>Curious George</tvshowtitle>
		<year>2006</year>
		<title>George Digs Worms</title>
		<premiered>2008-12-01</premiered>
		<season>3</season>
		<episode>13</episode>
		<thumbnail>http://thetvdb.com/banners/episodes/79429/414145.jpg</thumbnail>
		</meta>
	<link>
		<sublink>search</sublink>
		<sublink>searchsd</sublink>
	</link>
</item>

<item>
	<title>Curious George S03E14 - Everything Old is New Again</title>
	<meta>
		<content>episode</content>
		<imdb>tt0449545</imdb>
		<tvdb>79429</tvdb>
		<tvshowtitle>Curious George</tvshowtitle>
		<year>2006</year>
		<title>Everything Old is New Again</title>
		<premiered>2008-12-01</premiered>
		<season>3</season>
		<episode>14</episode>
		<thumbnail>http://thetvdb.com/banners/episodes/79429/1228531.jpg</thumbnail>
		</meta>
	<link>
		<sublink>search</sublink>
		<sublink>searchsd</sublink>
	</link>
</item>

<item>
	<title>Curious George S03E15 - Wheels on the Bus</title>
	<meta>
		<content>episode</content>
		<imdb>tt0449545</imdb>
		<tvdb>79429</tvdb>
		<tvshowtitle>Curious George</tvshowtitle>
		<year>2006</year>
		<title>Wheels on the Bus</title>
		<premiered>2009-02-16</premiered>
		<season>3</season>
		<episode>15</episode>
		<thumbnail>http://thetvdb.com/banners/episodes/79429/2317011.jpg</thumbnail>
		</meta>
	<link>
		<sublink>search</sublink>
		<sublink>searchsd</sublink>
	</link>
</item>

<item>
	<title>Curious George S03E16 - Seed Trouble</title>
	<meta>
		<content>episode</content>
		<imdb>tt0449545</imdb>
		<tvdb>79429</tvdb>
		<tvshowtitle>Curious George</tvshowtitle>
		<year>2006</year>
		<title>Seed Trouble</title>
		<premiered>2009-02-16</premiered>
		<season>3</season>
		<episode>16</episode>
		<thumbnail>http://thetvdb.com/banners/episodes/79429/2317021.jpg</thumbnail>
		</meta>
	<link>
		<sublink>search</sublink>
		<sublink>searchsd</sublink>
	</link>
</item>

<item>
	<title>Curious George S03E17 - Fun-Ball Tally</title>
	<meta>
		<content>episode</content>
		<imdb>tt0449545</imdb>
		<tvdb>79429</tvdb>
		<tvshowtitle>Curious George</tvshowtitle>
		<year>2006</year>
		<title>Fun-Ball Tally</title>
		<premiered>2009-02-17</premiered>
		<season>3</season>
		<episode>17</episode>
		<thumbnail>http://thetvdb.com/banners/episodes/79429/2317031.jpg</thumbnail>
		</meta>
	<link>
		<sublink>search</sublink>
		<sublink>searchsd</sublink>
	</link>
</item>

<item>
	<title>Curious George S03E18 - Red Sky at Night Monkey's Delight</title>
	<meta>
		<content>episode</content>
		<imdb>tt0449545</imdb>
		<tvdb>79429</tvdb>
		<tvshowtitle>Curious George</tvshowtitle>
		<year>2006</year>
		<title>Red Sky at Night Monkey's Delight</title>
		<premiered>2009-02-17</premiered>
		<season>3</season>
		<episode>18</episode>
		<thumbnail>http://thetvdb.com/banners/episodes/79429/2317041.jpg</thumbnail>
		</meta>
	<link>
		<sublink>search</sublink>
		<sublink>searchsd</sublink>
	</link>
</item>

<item>
	<title>Curious George S03E19 - Shipwrecked With Hundley</title>
	<meta>
		<content>episode</content>
		<imdb>tt0449545</imdb>
		<tvdb>79429</tvdb>
		<tvshowtitle>Curious George</tvshowtitle>
		<year>2006</year>
		<title>Shipwrecked With Hundley</title>
		<premiered>2009-02-18</premiered>
		<season>3</season>
		<episode>19</episode>
		<thumbnail>http://thetvdb.com/banners/episodes/79429/2317051.jpg</thumbnail>
		</meta>
	<link>
		<sublink>search</sublink>
		<sublink>searchsd</sublink>
	</link>
</item>

<item>
	<title>Curious George S03E20 - Chasing Rainbows</title>
	<meta>
		<content>episode</content>
		<imdb>tt0449545</imdb>
		<tvdb>79429</tvdb>
		<tvshowtitle>Curious George</tvshowtitle>
		<year>2006</year>
		<title>Chasing Rainbows</title>
		<premiered>2009-02-18</premiered>
		<season>3</season>
		<episode>20</episode>
		<thumbnail>http://thetvdb.com/banners/episodes/79429/2317061.jpg</thumbnail>
		</meta>
	<link>
		<sublink>search</sublink>
		<sublink>searchsd</sublink>
	</link>
</item>

<item>
	<title>Curious George S03E21 - Night of the Weiner Dog</title>
	<meta>
		<content>episode</content>
		<imdb>tt0449545</imdb>
		<tvdb>79429</tvdb>
		<tvshowtitle>Curious George</tvshowtitle>
		<year>2006</year>
		<title>Night of the Weiner Dog</title>
		<premiered>2009-04-22</premiered>
		<season>3</season>
		<episode>21</episode>
		<thumbnail>http://thetvdb.com/banners/episodes/79429/2317071.jpg</thumbnail>
		</meta>
	<link>
		<sublink>search</sublink>
		<sublink>searchsd</sublink>
	</link>
</item>

<item>
	<title>Curious George S03E22 - Animal Trackers</title>
	<meta>
		<content>episode</content>
		<imdb>tt0449545</imdb>
		<tvdb>79429</tvdb>
		<tvshowtitle>Curious George</tvshowtitle>
		<year>2006</year>
		<title>Animal Trackers</title>
		<premiered>2009-04-22</premiered>
		<season>3</season>
		<episode>22</episode>
		<thumbnail>http://thetvdb.com/banners/episodes/79429/2317081.jpg</thumbnail>
		</meta>
	<link>
		<sublink>search</sublink>
		<sublink>searchsd</sublink>
	</link>
</item>
