
##########################################################################################

<cache>10800</cache>
<thumbnail>http://thetvdb.com/banners/seasons/78901-7-6.jpg</thumbnail>
<fanart>http://thetvdb.com/banners/fanart/original/78901-85.jpg</fanart>
##########################################################################################

<item>
<title>Supernatural S07E01 - Meet the New Boss</title>
<meta>
<content>episode</content>
<imdb>tt0460681</imdb>
<tvdb>78901</tvdb>
<tvshowtitle>Supernatural</tvshowtitle>
<year>2005</year>
<title>Meet the New Boss</title>
<premiered>2011-09-23</premiered>
<season>7</season>
<episode>1</episode>
</meta>
<link>
<sublink>search</sublink>
<sublink>searchsd</sublink>
</link>
</item>

<item>
<title>Supernatural S07E02 - Hello, Cruel World</title>
<meta>
<content>episode</content>
<imdb>tt0460681</imdb>
<tvdb>78901</tvdb>
<tvshowtitle>Supernatural</tvshowtitle>
<year>2005</year>
<title>Hello, Cruel World</title>
<premiered>2011-09-30</premiered>
<season>7</season>
<episode>2</episode>
</meta>
<link>
<sublink>search</sublink>
<sublink>searchsd</sublink>
</link>
</item>

<item>
<title>Supernatural S07E03 - The Girl Next Door</title>
<meta>
<content>episode</content>
<imdb>tt0460681</imdb>
<tvdb>78901</tvdb>
<tvshowtitle>Supernatural</tvshowtitle>
<year>2005</year>
<title>The Girl Next Door</title>
<premiered>2011-10-07</premiered>
<season>7</season>
<episode>3</episode>
</meta>
<link>
<sublink>search</sublink>
<sublink>searchsd</sublink>
</link>
</item>

<item>
<title>Supernatural S07E04 - Defending Your Life</title>
<meta>
<content>episode</content>
<imdb>tt0460681</imdb>
<tvdb>78901</tvdb>
<tvshowtitle>Supernatural</tvshowtitle>
<year>2005</year>
<title>Defending Your Life</title>
<premiered>2011-10-14</premiered>
<season>7</season>
<episode>4</episode>
</meta>
<link>
<sublink>search</sublink>
<sublink>searchsd</sublink>
</link>
</item>

<item>
<title>Supernatural S07E05 - Shut Up, Dr. Phil</title>
<meta>
<content>episode</content>
<imdb>tt0460681</imdb>
<tvdb>78901</tvdb>
<tvshowtitle>Supernatural</tvshowtitle>
<year>2005</year>
<title>Shut Up, Dr. Phil</title>
<premiered>2011-10-21</premiered>
<season>7</season>
<episode>5</episode>
</meta>
<link>
<sublink>search</sublink>
<sublink>searchsd</sublink>
</link>
</item>

<item>
<title>Supernatural S07E06 - Slash Fiction</title>
<meta>
<content>episode</content>
<imdb>tt0460681</imdb>
<tvdb>78901</tvdb>
<tvshowtitle>Supernatural</tvshowtitle>
<year>2005</year>
<title>Slash Fiction</title>
<premiered>2011-10-28</premiered>
<season>7</season>
<episode>6</episode>
</meta>
<link>
<sublink>search</sublink>
<sublink>searchsd</sublink>
</link>
</item>

<item>
<title>Supernatural S07E07 - The Mentalists</title>
<meta>
<content>episode</content>
<imdb>tt0460681</imdb>
<tvdb>78901</tvdb>
<tvshowtitle>Supernatural</tvshowtitle>
<year>2005</year>
<title>The Mentalists</title>
<premiered>2011-11-04</premiered>
<season>7</season>
<episode>7</episode>
</meta>
<link>
<sublink>search</sublink>
<sublink>searchsd</sublink>
</link>
</item>

<item>
<title>Supernatural S07E08 - Season Seven, Time for a Wedding!</title>
<meta>
<content>episode</content>
<imdb>tt0460681</imdb>
<tvdb>78901</tvdb>
<tvshowtitle>Supernatural</tvshowtitle>
<year>2005</year>
<title>Season Seven, Time for a Wedding!</title>
<premiered>2011-11-11</premiered>
<season>7</season>
<episode>8</episode>
</meta>
<link>
<sublink>search</sublink>
<sublink>searchsd</sublink>
</link>
</item>

<item>
<title>Supernatural S07E09 - How to Win Friends and Influence Monsters</title>
<meta>
<content>episode</content>
<imdb>tt0460681</imdb>
<tvdb>78901</tvdb>
<tvshowtitle>Supernatural</tvshowtitle>
<year>2005</year>
<title>How to Win Friends and Influence Monsters</title>
<premiered>2011-11-18</premiered>
<season>7</season>
<episode>9</episode>
</meta>
<link>
<sublink>search</sublink>
<sublink>searchsd</sublink>
</link>
</item>

<item>
<title>Supernatural S07E10 - Death's Door</title>
<meta>
<content>episode</content>
<imdb>tt0460681</imdb>
<tvdb>78901</tvdb>
<tvshowtitle>Supernatural</tvshowtitle>
<year>2005</year>
<title>Death's Door</title>
<premiered>2011-12-02</premiered>
<season>7</season>
<episode>10</episode>
</meta>
<link>
<sublink>search</sublink>
<sublink>searchsd</sublink>
</link>
</item>

<item>
<title>Supernatural S07E11 - Adventures in Babysitting</title>
<meta>
<content>episode</content>
<imdb>tt0460681</imdb>
<tvdb>78901</tvdb>
<tvshowtitle>Supernatural</tvshowtitle>
<year>2005</year>
<title>Adventures in Babysitting</title>
<premiered>2012-01-06</premiered>
<season>7</season>
<episode>11</episode>
</meta>
<link>
<sublink>search</sublink>
<sublink>searchsd</sublink>
</link>
</item>

<item>
<title>Supernatural S07E12 - Time After Time</title>
<meta>
<content>episode</content>
<imdb>tt0460681</imdb>
<tvdb>78901</tvdb>
<tvshowtitle>Supernatural</tvshowtitle>
<year>2005</year>
<title>Time After Time</title>
<premiered>2012-01-13</premiered>
<season>7</season>
<episode>12</episode>
</meta>
<link>
<sublink>search</sublink>
<sublink>searchsd</sublink>
</link>
</item>

<item>
<title>Supernatural S07E13 - The Slice Girls</title>
<meta>
<content>episode</content>
<imdb>tt0460681</imdb>
<tvdb>78901</tvdb>
<tvshowtitle>Supernatural</tvshowtitle>
<year>2005</year>
<title>The Slice Girls</title>
<premiered>2012-02-03</premiered>
<season>7</season>
<episode>13</episode>
</meta>
<link>
<sublink>search</sublink>
<sublink>searchsd</sublink>
</link>
</item>

<item>
<title>Supernatural S07E14 - Plucky Pennywhistle's Magical Menagerie</title>
<meta>
<content>episode</content>
<imdb>tt0460681</imdb>
<tvdb>78901</tvdb>
<tvshowtitle>Supernatural</tvshowtitle>
<year>2005</year>
<title>Plucky Pennywhistle's Magical Menagerie</title>
<premiered>2012-02-10</premiered>
<season>7</season>
<episode>14</episode>
</meta>
<link>
<sublink>search</sublink>
<sublink>searchsd</sublink>
</link>
</item>

<item>
<title>Supernatural S07E15 - Repo Man</title>
<meta>
<content>episode</content>
<imdb>tt0460681</imdb>
<tvdb>78901</tvdb>
<tvshowtitle>Supernatural</tvshowtitle>
<year>2005</year>
<title>Repo Man</title>
<premiered>2012-02-17</premiered>
<season>7</season>
<episode>15</episode>
</meta>
<link>
<sublink>search</sublink>
<sublink>searchsd</sublink>
</link>
</item>

<item>
<title>Supernatural S07E16 - Out With the Old</title>
<meta>
<content>episode</content>
<imdb>tt0460681</imdb>
<tvdb>78901</tvdb>
<tvshowtitle>Supernatural</tvshowtitle>
<year>2005</year>
<title>Out With the Old</title>
<premiered>2012-03-16</premiered>
<season>7</season>
<episode>16</episode>
</meta>
<link>
<sublink>search</sublink>
<sublink>searchsd</sublink>
</link>
</item>

<item>
<title>Supernatural S07E17 - The Born-Again Identity</title>
<meta>
<content>episode</content>
<imdb>tt0460681</imdb>
<tvdb>78901</tvdb>
<tvshowtitle>Supernatural</tvshowtitle>
<year>2005</year>
<title>The Born-Again Identity</title>
<premiered>2012-03-23</premiered>
<season>7</season>
<episode>17</episode>
</meta>
<link>
<sublink>search</sublink>
<sublink>searchsd</sublink>
</link>
</item>

<item>
<title>Supernatural S07E18 - Party On, Garth</title>
<meta>
<content>episode</content>
<imdb>tt0460681</imdb>
<tvdb>78901</tvdb>
<tvshowtitle>Supernatural</tvshowtitle>
<year>2005</year>
<title>Party On, Garth</title>
<premiered>2012-03-30</premiered>
<season>7</season>
<episode>18</episode>
</meta>
<link>
<sublink>search</sublink>
<sublink>searchsd</sublink>
</link>
</item>

<item>
<title>Supernatural S07E19 - Of Grave Importance</title>
<meta>
<content>episode</content>
<imdb>tt0460681</imdb>
<tvdb>78901</tvdb>
<tvshowtitle>Supernatural</tvshowtitle>
<year>2005</year>
<title>Of Grave Importance</title>
<premiered>2012-04-20</premiered>
<season>7</season>
<episode>19</episode>
</meta>
<link>
<sublink>search</sublink>
<sublink>searchsd</sublink>
</link>
</item>

<item>
<title>Supernatural S07E20 - The Girl with the Dungeons and Dragons Tattoo</title>
<meta>
<content>episode</content>
<imdb>tt0460681</imdb>
<tvdb>78901</tvdb>
<tvshowtitle>Supernatural</tvshowtitle>
<year>2005</year>
<title>The Girl with the Dungeons and Dragons Tattoo</title>
<premiered>2012-04-27</premiered>
<season>7</season>
<episode>20</episode>
</meta>
<link>
<sublink>search</sublink>
<sublink>searchsd</sublink>
</link>
</item>

<item>
<title>Supernatural S07E21 - Reading is Fundamental</title>
<meta>
<content>episode</content>
<imdb>tt0460681</imdb>
<tvdb>78901</tvdb>
<tvshowtitle>Supernatural</tvshowtitle>
<year>2005</year>
<title>Reading is Fundamental</title>
<premiered>2012-05-04</premiered>
<season>7</season>
<episode>21</episode>
</meta>
<link>
<sublink>search</sublink>
<sublink>searchsd</sublink>
</link>
</item>

<item>
<title>Supernatural S07E22 - There Will Be Blood</title>
<meta>
<content>episode</content>
<imdb>tt0460681</imdb>
<tvdb>78901</tvdb>
<tvshowtitle>Supernatural</tvshowtitle>
<year>2005</year>
<title>There Will Be Blood</title>
<premiered>2012-05-11</premiered>
<season>7</season>
<episode>22</episode>
</meta>
<link>
<sublink>search</sublink>
<sublink>searchsd</sublink>
</link>
</item>

<item>
<title>Supernatural S07E23 - Survival of the Fittest</title>
<meta>
<content>episode</content>
<imdb>tt0460681</imdb>
<tvdb>78901</tvdb>
<tvshowtitle>Supernatural</tvshowtitle>
<year>2005</year>
<title>Survival of the Fittest</title>
<premiered>2012-05-18</premiered>
<season>7</season>
<episode>23</episode>
</meta>
<link>
<sublink>search</sublink>
<sublink>searchsd</sublink>
</link>
</item>
