##########################################################################################

<cache>10800</cache>
##########################################################################################
<item>
	<title>The Karate Kid (1984)</title>
	<link>
		<sublink>search</sublink>
		<sublink>searchsd</sublink>
	</link>
	<thumbnail>https://image.tmdb.org/t/p/original/5kKor5pZ3ov08CAstSyk7FGDKVN.jpg</thumbnail>
	<fanart>https://image.tmdb.org/t/p/original/lpJGmjxZ9ONC4efcnQdbyYyxFR5.jpg</fanart>
	<content>movie</content>
	<meta>
		<title>The Karate Kid</title>
		<year>1984</year>
		<imdb>tt0087538</imdb>
	</meta>
</item>

<item>
	<title>The Karate Kid Part II (1986)</title>
	<link>
		<sublink>search</sublink>
		<sublink>searchsd</sublink>
	</link>
	<thumbnail>https://image.tmdb.org/t/p/original/4zmEPGKrD3sgjHZUs99tknEBaJy.jpg</thumbnail>
	<fanart>https://image.tmdb.org/t/p/original/5CLE7S27lRHB4euOsrtvW9EM795.jpg</fanart>
	<content>movie</content>
	<meta>
		<title>The Karate Kid Part II</title>
		<year>1986</year>
		<imdb>tt0091326</imdb>
	</meta>
</item>

<item>
	<title>The Karate Kid Part III (1989)</title>
	<link>
		<sublink>search</sublink>
		<sublink>searchsd</sublink>
	</link>
	<thumbnail>https://image.tmdb.org/t/p/original/2Z0EJl11kOSPMMvHqZ4r5Csh7Ph.jpg</thumbnail>
	<fanart>https://image.tmdb.org/t/p/original/sJ8hujzwlxomD2lOzPhAiIfT1Mh.jpg</fanart>
	<content>movie</content>
	<meta>
		<title>The Karate Kid Part III</title>
		<year>1989</year>
		<imdb>tt0097647</imdb>
	</meta>
</item>

<item>
	<title>The Next Karate Kid (1994)</title>
	<link>
		<sublink>search</sublink>
		<sublink>searchsd</sublink>
	</link>
	<thumbnail>https://image.tmdb.org/t/p/original/gu5SOBWsoxDy6mWKAkOt20zTXOb.jpg</thumbnail>
	<fanart>https://image.tmdb.org/t/p/original/e7pmtrKg9WHVdPWjFNL7FJPoEiV.jpg</fanart>
	<content>movie</content>
	<meta>
		<title>The Next Karate Kid</title>
		<year>1994</year>
		<imdb>tt0110657</imdb>
	</meta>
</item>
