##########################################################################################

<cache>10800</cache>
##########################################################################################

<item>
	<title>The Purge (2013)</title>
	<link>
		<sublink>search</sublink>
		<sublink>searchsd</sublink>
	</link>
	<thumbnail>https://image.tmdb.org/t/p/original/tGGJOuLHX7UDlTz57sjfhW1qreP.jpg</thumbnail>
	<fanart>https://image.tmdb.org/t/p/original/z6LEqUrlfK0oM3xuTbXABVdaX0Y.jpg</fanart>
	<content>movie</content>
	<meta>
		<title>The Purge</title>
		<year>2013</year>
		<imdb>tt2184339</imdb>
	</meta>
</item>

<item>
	<title>The Purge: Anarchy (2014)</title>
	<link>
		<sublink>search</sublink>
		<sublink>searchsd</sublink>
	</link>
	<thumbnail>https://image.tmdb.org/t/p/original/l1DRl40x2OWUoPP42v8fjKdS1Z3.jpg</thumbnail>
	<fanart>https://image.tmdb.org/t/p/original/zWGAnbxjjwY3xFGuOeR26LGbBlG.jpg</fanart>
	<content>movie</content>
	<meta>
		<title>The Purge: Anarchy</title>
		<year>2014</year>
		<imdb>tt2975578</imdb>
	</meta>
</item>

<item>
	<title>The Purge: Election Year (2016)</title>
	<link>
		<sublink>search</sublink>
		<sublink>searchsd</sublink>
	</link>
	<thumbnail>https://image.tmdb.org/t/p/original/bjOJFjUffRZQpNQ9g3yvc9F6LBM.jpg</thumbnail>
	<fanart>https://image.tmdb.org/t/p/original/lPhsKTtycmbp6bzJAG662Pd5U3N.jpg</fanart>
	<content>movie</content>
	<meta>
		<title>The Purge: Election Year</title>
		<year>2016</year>
		<imdb>tt4094724</imdb>
	</meta>
</item>
