################################################################################
<fanart>https://www.thetvdb.com/banners/fanart/original/336522-1.jpg</fanart>
<thumbnail>https://www.thetvdb.com/banners/posters/336522-1.jpg</thumbnail>
#The End Of The F***ing World#
################################################################################


<item>
  <title>[B]The End Of The F***ing World - 	Episode 1[/B]</title>
  <meta>
    <content>episode</content>
    <imdb>tt6257970</imdb>
    <tvdb>336522</tvdb>
    <tvshowtitle>The End Of The F***ing World</tvshowtitle>
    <year>2017</year>
    <title>
  <title>Episode 1</title>
    <premiered>2017-10-24</premiered>
    <season>1</season>
    <episode>1</episode>
  </meta>
  <link>
    <sublink>search</sublink>
    <sublink>searchsd</sublink>
  </link>
  <thumbnail></thumbnail>
  <fanart></fanart>
</item>


<item>
  <title>[B]The End Of The F***ing World -Episode 2[/B]</title>
  <meta>
    <content>episode</content>
    <imdb>tt6257970</imdb>
    <tvdb>336522</tvdb>
    <tvshowtitle>The End Of The F***ing World</tvshowtitle>
    <year>2017</year>
    <title>Episode 2</title>
    <premiered>2017-10-24</premiered>
    <season>1</season>
    <episode>2</episode>
  </meta>
  <link>
    <sublink>search</sublink>
    <sublink>searchsd</sublink>
  </link>
  <thumbnail></thumbnail>
  <fanart></fanart>
</item>


<item>
  <title>[B]The End Of The F***ing World - Episode 3[/B]</title>
  <meta>
    <content>episode</content>
    <imdb>tt6257970</imdb>
    <tvdb>336522</tvdb>
    <tvshowtitle>The End Of The F***ing World</tvshowtitle>
    <year>2017</year>
    <title>Episode 3</title>
    <premiered>2017-10-24</premiered>
    <season>1</season>
    <episode>3</episode>
  </meta>
  <link>
    <sublink>search</sublink>
    <sublink>searchsd</sublink>
  </link>
  <thumbnail></thumbnail>
  <fanart></fanart>
</item>


<item>
  <title>[B]The End Of The F***ing World - Episode 4[/B]</title>
  <meta>
    <content>episode</content>
    <imdb>tt6257970</imdb>
    <tvdb>336522</tvdb>
    <tvshowtitle>The End Of The F***ing World</tvshowtitle>
    <year>2017</year>
    <title>Episode 4</title>
    <premiered>2017-10-24</premiered>
    <season>1</season>
    <episode>4</episode>
  </meta>
  <link>
    <sublink>search</sublink>
    <sublink>searchsd</sublink>
  </link>
  <thumbnail></thumbnail>
  <fanart></fanart>
</item>


<item>
  <title>[B]The End Of The F***ing World - Episode 5[/B]</title>
  <meta>
    <content>episode</content>
    <imdb>tt6257970</imdb>
    <tvdb>336522</tvdb>
    <tvshowtitle>The End Of The F***ing World</tvshowtitle>
    <year>2017</year>
    <title>Episode 5</title>
    <premiered>2017-10-24</premiered>
    <season>1</season>
    <episode>5</episode>
  </meta>
  <link>
    <sublink>search</sublink>
    <sublink>searchsd</sublink>
  </link>
  <thumbnail></thumbnail>
  <fanart></fanart>
</item>


<item>
  <title>[B]The End Of The F***ing World - Episode 6[/B]</title>
  <meta>
    <content>episode</content>
    <imdb>tt6257970</imdb>
    <tvdb>336522</tvdb>
    <tvshowtitle>The End Of The F***ing World</tvshowtitle>
    <year>2017</year>
    <title>Episode 6</title>
    <premiered>2017-10-24</premiered>
    <season>1</season>
    <episode>6</episode>
  </meta>
  <link>
    <sublink>search</sublink>
    <sublink>searchsd</sublink>
  </link>
  <thumbnail></thumbnail>
  <fanart></fanart>
</item>


<item>
  <title>[B]The End Of The F***ing World - Episode 7[/B]</title>
  <meta>
    <content>episode</content>
    <imdb>tt6257970</imdb>
    <tvdb>336522</tvdb>
    <tvshowtitle>The End Of The F***ing World</tvshowtitle>
    <year>2017</year>
    <title>Episode 7</title>
    <premiered>2017-10-24</premiered>
    <season>1</season>
    <episode>7</episode>
  </meta>
  <link>
    <sublink>search</sublink>
    <sublink>searchsd</sublink>
  </link>
  <thumbnail></thumbnail>
  <fanart></fanart>
</item>


<item>
  <title>[B]The End Of The F***ing World - Episode 8[/B]</title>
  <meta>
    <content>episode</content>
    <imdb>tt6257970</imdb>
    <tvdb>336522</tvdb>
    <tvshowtitle>The End Of The F***ing World</tvshowtitle>
    <year>2017</year>
    <title>Episode 8</title>
    <premiered>2017-10-24</premiered>
    <season>1</season>
    <episode>8</episode>
  </meta>
  <link>
    <sublink>search</sublink>
    <sublink>searchsd</sublink>
  </link>
  <thumbnail></thumbnail>
  <fanart></fanart>
</item>
